{
  "name": "mn-toast",
  "type": "registry:ui",
  "files": [
    {
      "path": "components/maranello/feedback/mn-toast.tsx",
      "content": "\"use client\"\n\nimport { useCallback, useEffect, useState } from \"react\"\nimport { cva, type VariantProps } from \"class-variance-authority\"\n\nimport { cn } from \"@/lib/utils\"\n\n/* ── Types ─────────────────────────────────────────────── */\n\ntype ToastVariant = \"success\" | \"error\" | \"warning\" | \"info\"\n\ninterface ToastData {\n  id: string\n  title?: string\n  message: string\n  variant: ToastVariant\n  duration: number\n}\n\ninterface ToastOptions {\n  title?: string\n  message: string\n  variant?: ToastVariant\n  duration?: number\n}\n\n/* ── CVA variants ──────────────────────────────────────── */\n\nconst toastVariants = cva(\n  \"pointer-events-auto flex items-start gap-3 rounded-lg border-l-4 px-4 py-3 shadow-[0_8px_24px_rgba(0,0,0,.4)] min-w-[280px] max-w-[420px] transition-all duration-300\",\n  {\n    variants: {\n      variant: {\n        success: \"border-l-green-500 bg-neutral-900 text-neutral-300\",\n        error: \"border-l-red-500 bg-neutral-900 text-neutral-300\",\n        warning: \"border-l-amber-500 bg-neutral-900 text-neutral-300\",\n        info: \"border-l-sky-500 bg-neutral-900 text-neutral-300\",\n      },\n    },\n    defaultVariants: { variant: \"info\" },\n  },\n)\n\ntype ToastVariantProps = VariantProps<typeof toastVariants>\n\nconst icons: Record<ToastVariant, string> = {\n  success: \"\\u2713\",\n  warning: \"\\u26A0\",\n  error: \"\\u2716\",\n  info: \"\\u2139\",\n}\n\n/* ── Module-level store ────────────────────────────────── */\n\nlet nextId = 0\nlet store: ToastData[] = []\nlet listeners: Array<(t: ToastData[]) => void> = []\n\nfunction emit() {\n  const snapshot = [...store]\n  listeners.forEach((fn) => fn(snapshot))\n}\n\nfunction dismiss(id: string) {\n  store = store.filter((t) => t.id !== id)\n  emit()\n}\n\n/* ── Public toast() trigger ────────────────────────────── */\n\nfunction toast(opts: ToastOptions): string {\n  const id = String(++nextId)\n  store = [\n    ...store,\n    {\n      id,\n      message: opts.message,\n      title: opts.title,\n      variant: opts.variant ?? \"info\",\n      duration: opts.duration ?? 5000,\n    },\n  ]\n  emit()\n  return id\n}\n\ntoast.success = (message: string, opts?: Omit<ToastOptions, \"message\" | \"variant\">) =>\n  toast({ ...opts, message, variant: \"success\" })\ntoast.error = (message: string, opts?: Omit<ToastOptions, \"message\" | \"variant\">) =>\n  toast({ ...opts, message, variant: \"error\" })\ntoast.warning = (message: string, opts?: Omit<ToastOptions, \"message\" | \"variant\">) =>\n  toast({ ...opts, message, variant: \"warning\" })\ntoast.info = (message: string, opts?: Omit<ToastOptions, \"message\" | \"variant\">) =>\n  toast({ ...opts, message, variant: \"info\" })\ntoast.dismiss = dismiss\n\n/* ── Hooks ─────────────────────────────────────────────── */\n\nfunction useToasts() {\n  const [state, setState] = useState<ToastData[]>([])\n  useEffect(() => {\n    listeners.push(setState)\n    return () => {\n      listeners = listeners.filter((fn) => fn !== setState)\n    }\n  }, [])\n  return state\n}\n\n/* ── Toast item (internal) ─────────────────────────────── */\n\nfunction ToastItem({\n  data,\n  onDismiss,\n}: {\n  data: ToastData\n  onDismiss: () => void\n}) {\n  const [removing, setRemoving] = useState(false)\n  const isUrgent = data.variant === \"error\" || data.variant === \"warning\"\n\n  const handleDismiss = useCallback(() => {\n    setRemoving(true)\n    setTimeout(onDismiss, 300)\n  }, [onDismiss])\n\n  useEffect(() => {\n    if (data.duration <= 0) return\n    const timer = setTimeout(handleDismiss, data.duration)\n    return () => clearTimeout(timer)\n  }, [data.duration, handleDismiss])\n\n  return (\n    <div\n      role={isUrgent ? \"alert\" : \"status\"}\n      aria-live={isUrgent ? \"assertive\" : \"polite\"}\n      className={cn(\n        toastVariants({ variant: data.variant }),\n        removing && \"translate-x-full opacity-0\",\n      )}\n    >\n      <span className=\"mt-0.5 shrink-0 text-lg\" aria-hidden=\"true\">\n        {icons[data.variant]}\n      </span>\n      <div className=\"min-w-0 flex-1\">\n        {data.title && (\n          <div className=\"mb-0.5 text-sm font-semibold text-neutral-100\">\n            {data.title}\n          </div>\n        )}\n        <div className=\"text-sm leading-snug\">{data.message}</div>\n      </div>\n      <button\n        type=\"button\"\n        onClick={handleDismiss}\n        className=\"shrink-0 cursor-pointer rounded px-1.5 py-0.5 text-neutral-400 hover:bg-neutral-700 hover:text-neutral-200\"\n        aria-label=\"Close\"\n      >\n        ✕\n      </button>\n    </div>\n  )\n}\n\n/* ── MnToast container (mount once in layout) ──────────── */\n\nfunction MnToast({ className }: { className?: string }) {\n  const items = useToasts()\n\n  if (items.length === 0) return null\n\n  return (\n    <div\n      aria-label=\"Notifications\"\n      className={cn(\n        \"pointer-events-none fixed inset-x-0 top-4 z-[9999] flex flex-col items-end gap-2 px-4\",\n        className,\n      )}\n    >\n      {items.map((t) => (\n        <ToastItem key={t.id} data={t} onDismiss={() => dismiss(t.id)} />\n      ))}\n    </div>\n  )\n}\n\nexport { MnToast, toast, toastVariants, type ToastVariantProps, type ToastOptions }\n",
      "type": "registry:ui"
    }
  ],
  "dependencies": [
    "class-variance-authority"
  ],
  "registryDependencies": []
}